py_concodese/__init__.py
py_concodese/main.py
py_concodese/bug_parsing/__init__.py
py_concodese/bug_parsing/bug_report.py
py_concodese/bug_parsing/xml_to_csv.py
py_concodese/combined_funcs/__init__.py
py_concodese/combined_funcs/indexer.py
py_concodese/examples/config.toml
py_concodese/ez_multiprocessing/__init__.py
py_concodese/ez_multiprocessing/ez_multi_processor.py
py_concodese/git_utils/__init__.py
py_concodese/git_utils/grammar_downloader.py
py_concodese/git_utils/grammar_repositories.json
py_concodese/jars/antlr-complete-4.5.jar
py_concodese/jars/clap-7.jar
py_concodese/jars/commons-lang-2.4.jar
py_concodese/jars/derby.jar
py_concodese/jars/derbyclient.jar
py_concodese/jars/idtk-7.jar
py_concodese/jars/intt-7.jar
py_concodese/jars/jbfe-0.1.0.jar
py_concodese/jars/jim-7c.jar
py_concodese/jars/jimdb-7.jar
py_concodese/jars/lucene-core-3.6.1.jar
py_concodese/jars/pathfinder-r79.jar
py_concodese/jars/slf4j-api-1.7.24.jar
py_concodese/jars/wordlists-0.0.1.jar
py_concodese/jars_other/intt-0.8.0.jar
py_concodese/jars_other/intt-0.8.11.jar
py_concodese/jars_other/intt-0.8.12a.jar
py_concodese/jvm_loader/__init__.py
py_concodese/jvm_loader/jvm_loader.py
py_concodese/lucene_handler/__init__.py
py_concodese/lucene_handler/lucene_helper.py
py_concodese/lucene_handler/nlp_base.py
py_concodese/lucene_handler/spacy_helper.py
py_concodese/scoring/__init__.py
py_concodese/scoring/bug_result.py
py_concodese/scoring/evaluation.py
py_concodese/scoring/file_rank_data.py
py_concodese/scoring/lexical_similarity.py
py_concodese/scoring/lexical_similarity_orig.py
py_concodese/scoring/make_scoring_configs.py
py_concodese/scoring/map_mrr.py
py_concodese/scoring/path_type.py
py_concodese/scoring/top_k.py
py_concodese/scoring/vsm.py
py_concodese/storage/__init__.py
py_concodese/storage/filebase.py
py_concodese/storage/modelless.py
py_concodese/storage/models.py
py_concodese/storage/sql_base.py
py_concodese/storage/sql_connector.py
py_concodese/tokenizers/__init__.py
py_concodese-1.1.2.dist-info/LICENSE.md
py_concodese-1.1.2.dist-info/METADATA
py_concodese-1.1.2.dist-info/WHEEL
py_concodese-1.1.2.dist-info/entry_points.txt
py_concodese-1.1.2.dist-info/top_level.txt
py_concodese-1.1.2.dist-info/zip-safe
py_concodese-1.1.2.dist-info/RECORD
