Metadata-Version: 2.1
Name: py-concodese
Version: 1.1.2
Summary: Given a bug report, suggests code files that may need to be fixed
License: BSD 3-Clause License
Keywords: bug localisation,recommender system
Classifier: Topic :: Software Development :: Bug Tracking
Classifier: License :: OSI Approved :: BSD License
Classifier: Programming Language :: Java
Classifier: Programming Language :: Python :: 3.8
Classifier: Intended Audience :: Developers
Classifier: Intended Audience :: Science/Research
Requires-Python: >=3.8
License-File: LICENSE.md
Requires-Dist: JPype1 (>=1.4.1)
Requires-Dist: toml (>=0.10.2)
Requires-Dist: nltk (>=3.8.1)
Requires-Dist: spacy (>=3.5.1)
Requires-Dist: SQLAlchemy (>=1.4.42)
Requires-Dist: tree-sitter (>=0.20.1)
Requires-Dist: GitPython (>=3.1.31)
Requires-Dist: dicttoxml (==1.7.16)
Requires-Dist: deepl (==1.14.0)
